momatrix/__init__.py
momatrix/matrix.py
momatrix/static/matrix.css
momatrix/static/matrix.js
momatrix-0.1.1.dist-info/WHEEL
momatrix-0.1.1.dist-info/entry_points.txt
momatrix-0.1.1.dist-info/METADATA
momatrix-0.1.1.dist-info/RECORD
